pytest_datadir_nng/__init__.py
pytest_datadir_nng-1.1.1.dist-info/entry_points.txt
pytest_datadir_nng-1.1.1.dist-info/LICENSE
pytest_datadir_nng-1.1.1.dist-info/WHEEL
pytest_datadir_nng-1.1.1.dist-info/METADATA
pytest_datadir_nng-1.1.1.dist-info/RECORD
