Metadata-Version: 2.1
Name: pytest-datadir-nng
Version: 1.1.1
Summary: Fixtures for pytest allowing test functions/methods to easily retrieve test resources from the local filesystem.
Home-page: https://github.com/jdidion/pytest-datadir-nng
License: BSD-3-Clause
Author: jdidion
Author-email: github@didion.net
Requires-Python: >=3.6,<4.0
Classifier: Development Status :: 5 - Production/Stable
Classifier: Intended Audience :: Developers
Classifier: License :: OSI Approved :: BSD License
Classifier: Operating System :: MacOS :: MacOS X
Classifier: Operating System :: Microsoft :: Windows
Classifier: Operating System :: POSIX
Classifier: Programming Language :: Python :: 3
Classifier: Programming Language :: Python :: 3.6
Classifier: Programming Language :: Python :: 3.7
Classifier: Programming Language :: Python :: 3.8
Classifier: Programming Language :: Python :: 3.9
Classifier: Programming Language :: Python :: 3.10
Classifier: Programming Language :: Python :: 3.11
Classifier: Programming Language :: Python :: 3
Classifier: Programming Language :: Python :: 3.10
Classifier: Programming Language :: Python :: 3.6
Classifier: Programming Language :: Python :: 3.7
Classifier: Programming Language :: Python :: 3.8
Classifier: Programming Language :: Python :: 3.9
Classifier: Topic :: Software Development :: Testing
Requires-Dist: pytest (>=7.0.0,<8.0.0)
Project-URL: Repository, https://github.com/jdidion/pytest-datadir-nng
